openapi_resolver/__init__.py
openapi_resolver/__main__.py
openapi_resolver-0.0.2.dist-info/METADATA
openapi_resolver-0.0.2.dist-info/RECORD
openapi_resolver-0.0.2.dist-info/WHEEL
openapi_resolver-0.0.2.dist-info/top_level.txt
