Metadata-Version: 2.1
Name: openapi-resolver
Version: 0.0.2
Summary: Resolve and bundle openapi v3 specs.
Home-page: https://github.com/ioggstream/openapi-resolver
Author: Roberto Polli
Author-email: robipolli@gmail.com
License: UNKNOWN
Keywords: openapi,rest,swagger
Platform: UNKNOWN
Classifier: Programming Language :: Python :: 3
Classifier: License :: OSI Approved :: MIT License
Classifier: Operating System :: OS Independent
Requires-Dist: pyyaml
Requires-Dist: six
